jupyterlab/__init__.py
jupyterlab/__main__.py
jupyterlab/_version.py
jupyterlab/browser-test.js
jupyterlab/browser_check.py
jupyterlab/commands.py
jupyterlab/coreconfig.py
jupyterlab/debuglog.py
jupyterlab/federated_labextensions.py
jupyterlab/jlpmapp.py
jupyterlab/labapp.py
jupyterlab/labextensions.py
jupyterlab/labhubapp.py
jupyterlab/node-version-check.js
jupyterlab/pytest_plugin.py
jupyterlab/semver.py
jupyterlab/serverextension.py
jupyterlab/style.js
jupyterlab/upgrade_extension.py
jupyterlab/utils.py
jupyterlab/extensions/__init__.py
jupyterlab/extensions/manager.py
jupyterlab/extensions/pypi.py
jupyterlab/extensions/readonly.py
jupyterlab/galata/__init__.py
jupyterlab/galata/@jupyterlab/galata-extension/build_log.json
jupyterlab/galata/@jupyterlab/galata-extension/package.json
jupyterlab/galata/@jupyterlab/galata-extension/static/lib_extension_index_js.193465adc9aa81a6b29f.js
jupyterlab/galata/@jupyterlab/galata-extension/static/remoteEntry.26f7de15c78755feea34.js
jupyterlab/galata/@jupyterlab/galata-extension/static/style.js
jupyterlab/handlers/__init__.py
jupyterlab/handlers/announcements.py
jupyterlab/handlers/build_handler.py
jupyterlab/handlers/error_handler.py
jupyterlab/handlers/extension_manager_handler.py
jupyterlab/handlers/plugin_manager_handler.py
jupyterlab/schemas/@jupyterlab/application-extension/commands.json
jupyterlab/schemas/@jupyterlab/application-extension/context-menu.json
jupyterlab/schemas/@jupyterlab/application-extension/package.json.orig
jupyterlab/schemas/@jupyterlab/application-extension/property-inspector.json
jupyterlab/schemas/@jupyterlab/application-extension/shell.json
jupyterlab/schemas/@jupyterlab/application-extension/top-bar.json
jupyterlab/schemas/@jupyterlab/apputils-extension/notification.json
jupyterlab/schemas/@jupyterlab/apputils-extension/package.json.orig
jupyterlab/schemas/@jupyterlab/apputils-extension/palette.json
jupyterlab/schemas/@jupyterlab/apputils-extension/print.json
sknotebook-4.1.0a2.dist-info/METADATA
sknotebook-4.1.0a2.dist-info/WHEEL
sknotebook-4.1.0a2.dist-info/entry_points.txt
sknotebook-4.1.0a2.dist-info/licenses/LICENSE
sknotebook-4.1.0a2.dist-info/RECORD
