Metadata-Version: 2.1
Name: sknotebook
Version: 4.1.0a2
Summary: JupyterLab computational environment
Project-URL: Homepage, https://jupyter.org
Project-URL: Changelog, https://jupyterlab.readthedocs.io/en/stable/getting_started/changelog.html
Project-URL: Documentation, https://jupyterlab.readthedocs.io
Project-URL: Source, https://github.com/jupyterlab/jupyterlab
Project-URL: Issues, https://github.com/jupyterlab/jupyterlab/issues/new/choose
Project-URL: Gitter, https://gitter.im/jupyterlab/jupyterlab
Project-URL: Pypi, https://pypi.org/project/jupyterlab
Author-email: Jupyter Development Team <jupyter@googlegroups.com>
License: Copyright (c) 2015-2022 Project Jupyter Contributors
License-File: LICENSE
Keywords: ipython,jupyter
Classifier: Development Status :: 5 - Production/Stable
Classifier: Framework :: Jupyter
Classifier: Framework :: Jupyter :: JupyterLab
Classifier: Framework :: Jupyter :: JupyterLab :: 4
Classifier: Intended Audience :: Developers
Classifier: Intended Audience :: Science/Research
Classifier: Intended Audience :: System Administrators
Classifier: License :: OSI Approved :: BSD License
Classifier: Programming Language :: Python
Classifier: Programming Language :: Python :: 3.8
Classifier: Programming Language :: Python :: 3.9
Classifier: Programming Language :: Python :: 3.10
Classifier: Programming Language :: Python :: 3.11
Requires-Python: >=3.8
Requires-Dist: async-lru>=1.0.0
Requires-Dist: importlib-metadata>=4.8.3; python_version < '3.10'
Requires-Dist: importlib-resources>=1.4; python_version < '3.9'
Requires-Dist: ipykernel
Requires-Dist: jinja2>=3.0.3
Requires-Dist: jupyter-core
Requires-Dist: jupyter-lsp>=2.0.0
Requires-Dist: jupyter-server<3,>=2.4.0
Requires-Dist: jupyterlab-language-pack-zh-cn
Requires-Dist: jupyterlab-server<3,>=2.19.0
Requires-Dist: notebook-shim>=0.2
Requires-Dist: packaging
Requires-Dist: tomli; python_version < '3.11'
Requires-Dist: tornado>=6.2.0
Requires-Dist: traitlets
Provides-Extra: dev
Requires-Dist: black[jupyter]==23.7.0; extra == 'dev'
Requires-Dist: build; extra == 'dev'
Requires-Dist: bump2version; extra == 'dev'
Requires-Dist: coverage; extra == 'dev'
Requires-Dist: hatch; extra == 'dev'
Requires-Dist: pre-commit; extra == 'dev'
Requires-Dist: pytest-cov; extra == 'dev'
Requires-Dist: ruff==0.0.292; extra == 'dev'
Provides-Extra: docs
Requires-Dist: jsx-lexer; extra == 'docs'
Requires-Dist: myst-parser; extra == 'docs'
Requires-Dist: pydata-sphinx-theme>=0.13.0; extra == 'docs'
Requires-Dist: pytest; extra == 'docs'
Requires-Dist: pytest-check-links; extra == 'docs'
Requires-Dist: pytest-tornasync; extra == 'docs'
Requires-Dist: sphinx-copybutton; extra == 'docs'
Requires-Dist: sphinx<7.3.0,>=1.8; extra == 'docs'
Provides-Extra: docs-screenshots
Requires-Dist: altair==5.1.1; extra == 'docs-screenshots'
Requires-Dist: ipython==8.16.1; extra == 'docs-screenshots'
Requires-Dist: ipywidgets==8.1.0; extra == 'docs-screenshots'
Requires-Dist: jupyterlab-geojson==3.4.0; extra == 'docs-screenshots'
Requires-Dist: jupyterlab-language-pack-zh-cn==4.0.post3; extra == 'docs-screenshots'
Requires-Dist: matplotlib==3.7.2; extra == 'docs-screenshots'
Requires-Dist: nbconvert>=7.0.0; extra == 'docs-screenshots'
Requires-Dist: pandas==2.1.1; extra == 'docs-screenshots'
Requires-Dist: scipy==1.11.1; extra == 'docs-screenshots'
Requires-Dist: vega-datasets==0.9.0; extra == 'docs-screenshots'
Provides-Extra: test
Requires-Dist: coverage; extra == 'test'
Requires-Dist: pytest-check-links>=0.7; extra == 'test'
Requires-Dist: pytest-console-scripts; extra == 'test'
Requires-Dist: pytest-cov; extra == 'test'
Requires-Dist: pytest-jupyter>=0.5.3; extra == 'test'
Requires-Dist: pytest-timeout; extra == 'test'
Requires-Dist: pytest-tornasync; extra == 'test'
Requires-Dist: pytest>=7.0; extra == 'test'
Requires-Dist: requests; extra == 'test'
Requires-Dist: requests-cache; extra == 'test'
Requires-Dist: virtualenv; extra == 'test'
